[{"BOARDID":"TQOB","TRADEDATE":"2015-02-06","SHORTNAME":"\u041E\u0424\u0417 25075","SECID":"SU25075RMFS1","NUMTRADES":1,"VALUE":995,"LOW":99.5,"HIGH":99.5,"CLOSE":99.5,"LEGALCLOSEPRICE":97.65,"ACCINT":4.34,"WAPRICE":99.5,"YIELDCLOSE":8.25,"OPEN":99.5,"VOLUME":1,"MARKETPRICE2":97.6605,"MARKETPRICE3":97.6605,"ADMITTEDQUOTE":97.6605,"MP2VALTRD":52673179.76,"MARKETPRICE3TRADESVALUE":52673179.76,"ADMITTEDVALUE":52673179.76,"MATDATE":"2015-07-15","DURATION":159,"YIELDATWAP":8.25,"IRICPICLOSE":null,"BEICLOSE":null,"COUPONPERCENT":null,"COUPONVALUE":null,"BUYBACKDATE":null,"LASTTRADEDATE":null,"FACEVALUE":1000,"CURRENCYID":"SUR","CBRCLOSE":null,"YIELDTOOFFER":null,"YIELDLASTCOUPON":null,"OFFERDATE":null,"FACEUNIT":"RUB"},{"BOARDID":"TQOB","TRADEDATE":"2015-02-06","SHORTNAME":"\u041E\u0424\u0417 25077","SECID":"SU25077RMFS7","NUMTRADES":0,"VALUE":0,"LOW":null,"HIGH":null,"CLOSE":null,"LEGALCLOSEPRICE":95.3,"ACCINT":3.22,"WAPRICE":null,"YIELDCLOSE":12.64,"OPEN":null,"VOLUME":0,"MARKETPRICE2":95.364,"MARKETPRICE3":95.364,"ADMITTEDQUOTE":95.364,"MP2VALTRD":227146515.23,"MARKETPRICE3TRADESVALUE":227146515.23,"ADMITTEDVALUE":227146515.23,"MATDATE":"2016-01-20","DURATION":341,"YIELDATWAP":null,"IRICPICLOSE":null,"BEICLOSE":null,"COUPONPERCENT":null,"COUPONVALUE":null,"BUYBACKDATE":null,"LASTTRADEDATE":null,"FACEVALUE":1000,"CURRENCYID":"SUR","CBRCLOSE":null,"YIELDTOOFFER":null,"YIELDLASTCOUPON":null,"OFFERDATE":null,"FACEUNIT":"RUB"},{"BOARDID":"TQOB","TRADEDATE":"2015-02-06","SHORTNAME":"\u041E\u0424\u0417 25079","SECID":"SU25079RMFS3","NUMTRADES":6,"VALUE":117209.5,"LOW":98.4,"HIGH":98.85,"CLOSE":98.85,"LEGALCLOSEPRICE":98.4297,"ACCINT":12.46,"WAPRICE":98.4954,"YIELDCLOSE":11.1,"OPEN":98.75,"VOLUME":119,"MARKETPRICE2":98.415,"MARKETPRICE3":98.415,"ADMITTEDQUOTE":98.415,"MP2VALTRD":449208468.87,"MARKETPRICE3TRADESVALUE":449208468.87,"ADMITTEDVALUE":449208468.87,"MATDATE":"2015-06-03","DURATION":117,"YIELDATWAP":12.38,"IRICPICLOSE":null,"BEICLOSE":null,"COUPONPERCENT":null,"COUPONVALUE":null,"BUYBACKDATE":null,"LASTTRADEDATE":null,"FACEVALUE":1000,"CURRENCYID":"SUR","CBRCLOSE":null,"YIELDTOOFFER":null,"YIELDLASTCOUPON":null,"OFFERDATE":null,"FACEUNIT":"RUB"},{"BOARDID":"TQOB","TRADEDATE":"2015-02-06","SHORTNAME":"\u041E\u0424\u0417 25080","SECID":"SU25080RMFS1","NUMTRADES":0,"VALUE":0,"LOW":null,"HIGH":null,"CLOSE":null,"LEGALCLOSEPRICE":88.65,"ACCINT":21.69,"WAPRICE":null,"YIELDCLOSE":12.57,"OPEN":null,"VOLUME":0,"MARKETPRICE2":88.5833,"MARKETPRICE3":88.5833,"ADMITTEDQUOTE":88.5833,"MP2VALTRD":15111416.8,"MARKETPRICE3TRADESVALUE":15111416.8,"ADMITTEDVALUE":15111416.8,"MATDATE":"2017-04-19","DURATION":735,"YIELDATWAP":null,"IRICPICLOSE":null,"BEICLOSE":null,"COUPONPERCENT":null,"COUPONVALUE":null,"BUYBACKDATE":null,"LASTTRADEDATE":null,"FACEVALUE":1000,"CURRENCYID":"SUR","CBRCLOSE":null,"YIELDTOOFFER":null,"YIELDLASTCOUPON":null,"OFFERDATE":null,"FACEUNIT":"RUR"},{"BOARDID":"TQOB","TRADEDATE":"2015-02-06","SHORTNAME":"\u041E\u0424\u0417 25081","SECID":"SU25081RMFS9","NUMTRADES":0,"VALUE":0,"LOW":null,"HIGH":null,"CLOSE":null,"LEGALCLOSEPRICE":83,"ACCINT":0.34,"WAPRICE":null,"YIELDCLOSE":15.45,"OPEN":null,"VOLUME":0,"MARKETPRICE2":83.6984,"MARKETPRICE3":83.6984,"ADMITTEDQUOTE":83.6984,"MP2VALTRD":4112939,"MARKETPRICE3TRADESVALUE":4112939,"ADMITTEDVALUE":4112939,"MATDATE":"2018-01-31","DURATION":1002,"YIELDATWAP":null,"IRICPICLOSE":null,"BEICLOSE":null,"COUPONPERCENT":null,"COUPONVALUE":null,"BUYBACKDATE":null,"LASTTRADEDATE":null,"FACEVALUE":1000,"CURRENCYID":"SUR","CBRCLOSE":null,"YIELDTOOFFER":null,"YIELDLASTCOUPON":null,"OFFERDATE":null,"FACEUNIT":"RUB"},{"BOARDID":"TQOB","TRADEDATE":"2015-02-06","SHORTNAME":"\u041E\u0424\u0417 25082","SECID":"SU25082RMFS7","NUMTRADES":0,"VALUE":0,"LOW":null,"HIGH":null,"CLOSE":null,"LEGALCLOSEPRICE":91.98,"ACCINT":14.14,"WAPRICE":null,"YIELDCLOSE":8.78,"OPEN":null,"VOLUME":0,"MARKETPRICE2":91.5001,"MARKETPRICE3":91.5001,"ADMITTEDQUOTE":91.5001,"MP2VALTRD":36632075.5,"MARKETPRICE3TRADESVALUE":36609198,"ADMITTEDVALUE":36632075.5,"MATDATE":"2016-05-11","DURATION":443,"YIELDATWAP":null,"IRICPICLOSE":null,"BEICLOSE":null,"COUPONPERCENT":null,"COUPONVALUE":null,"BUYBACKDATE":null,"LASTTRADEDATE":null,"FACEVALUE":1000,"CURRENCYID":"SUR","CBRCLOSE":null,"YIELDTOOFFER":null,"YIELDLASTCOUPON":null,"OFFERDATE":null,"FACEUNIT":"RUR"},{"BOARDID":"TQOB","TRADEDATE":"2015-02-06","SHORTNAME":"\u041E\u0424\u0417 26203","SECID":"SU26203RMFS8","NUMTRADES":0,"VALUE":0,"LOW":null,"HIGH":null,"CLOSE":null,"LEGALCLOSEPRICE":91.9,"ACCINT":0.38,"WAPRICE":null,"YIELDCLOSE":15.2,"OPEN":null,"VOLUME":0,"MARKETPRICE2":91.6017,"MARKETPRICE3":91.6017,"ADMITTEDQUOTE":91.6017,"MP2VALTRD":239887422.54,"MARKETPRICE3TRADESVALUE":239887422.54,"ADMITTEDVALUE":239887422.54,"MATDATE":"2016-08-03","DURATION":525,"YIELDATWAP":null,"IRICPICLOSE":null,"BEICLOSE":null,"COUPONPERCENT":null,"COUPONVALUE":null,"BUYBACKDATE":null,"LASTTRADEDATE":null,"FACEVALUE":1000,"CURRENCYID":"SUR","CBRCLOSE":null,"YIELDTOOFFER":null,"YIELDLASTCOUPON":null,"OFFERDATE":null,"FACEUNIT":"RUR"},{"BOARDID":"TQOB","TRADEDATE":"2015-02-06","SHORTNAME":"\u041E\u0424\u0417 26204","SECID":"SU26204RMFS6","NUMTRADES":0,"VALUE":0,"LOW":null,"HIGH":null,"CLOSE":null,"LEGALCLOSEPRICE":86,"ACCINT":28.97,"WAPRICE":null,"YIELDCLOSE":17.36,"OPEN":null,"VOLUME":0,"MARKETPRICE2":84.6636,"MARKETPRICE3":85.1366,"ADMITTEDQUOTE":84.6636,"MP2VALTRD":225403392.51,"MARKETPRICE3TRADESVALUE":106891570,"ADMITTEDVALUE":225403392.51,"MATDATE":"2018-03-15","DURATION":988,"YIELDATWAP":null,"IRICPICLOSE":null,"BEICLOSE":null,"COUPONPERCENT":null,"COUPONVALUE":null,"BUYBACKDATE":null,"LASTTRADEDATE":null,"FACEVALUE":1000,"CURRENCYID":"SUR","CBRCLOSE":null,"YIELDTOOFFER":null,"YIELDLASTCOUPON":null,"OFFERDATE":null,"FACEUNIT":"RUB"},{"BOARDID":"TQOB","TRADEDATE":"2015-02-06","SHORTNAME":"\u041E\u0424\u0417 26205","SECID":"SU26205RMFS3","NUMTRADES":0,"VALUE":0,"LOW":null,"HIGH":null,"CLOSE":null,"LEGALCLOSEPRICE":77.5,"ACCINT":22.28,"WAPRICE":null,"YIELDCLOSE":13.41,"OPEN":null,"VOLUME":0,"MARKETPRICE2":77.7093,"MARKETPRICE3":77.7093,"ADMITTEDQUOTE":77.7093,"MP2VALTRD":496563276,"MARKETPRICE3TRADESVALUE":496563276,"ADMITTEDVALUE":496563276,"MATDATE":"2021-04-14","DURATION":1722,"YIELDATWAP":null,"IRICPICLOSE":null,"BEICLOSE":null,"COUPONPERCENT":null,"COUPONVALUE":null,"BUYBACKDATE":null,"LASTTRADEDATE":null,"FACEVALUE":1000,"CURRENCYID":"SUR","CBRCLOSE":null,"YIELDTOOFFER":null,"YIELDLASTCOUPON":null,"OFFERDATE":null,"FACEUNIT":"RUB"},{"BOARDID":"TQOB","TRADEDATE":"2015-02-06","SHORTNAME":"\u041E\u0424\u0417 26206","SECID":"SU26206RMFS1","NUMTRADES":1,"VALUE":6318.9,"LOW":90.27,"HIGH":90.27,"CLOSE":90.27,"LEGALCLOSEPRICE":90.27,"ACCINT":10.34,"WAPRICE":90.27,"YIELDCLOSE":12.67,"OPEN":90.27,"VOLUME":7,"MARKETPRICE2":87.852,"MARKETPRICE3":87.852,"ADMITTEDQUOTE":87.852,"MP2VALTRD":5834251.73,"MARKETPRICE3TRADESVALUE":5834251.73,"ADMITTEDVALUE":5834251.73,"MATDATE":"2017-06-14","DURATION":792,"YIELDATWAP":12.67,"IRICPICLOSE":null,"BEICLOSE":null,"COUPONPERCENT":null,"COUPONVALUE":null,"BUYBACKDATE":null,"LASTTRADEDATE":null,"FACEVALUE":1000,"CURRENCYID":"SUR","CBRCLOSE":null,"YIELDTOOFFER":null,"YIELDLASTCOUPON":null,"OFFERDATE":null,"FACEUNIT":"RUR"},{"BOARDID":"TQOB","TRADEDATE":"2015-02-06","SHORTNAME":"\u041E\u0424\u0417 26207","SECID":"SU26207RMFS9","NUMTRADES":1,"VALUE":770,"LOW":77,"HIGH":77,"CLOSE":77,"LEGALCLOSEPRICE":76.3999,"ACCINT":37.96,"WAPRICE":77,"YIELDCLOSE":12.13,"OPEN":77,"VOLUME":1,"MARKETPRICE2":76.6808,"MARKETPRICE3":76.6808,"ADMITTEDQUOTE":76.6808,"MP2VALTRD":201842315.84,"MARKETPRICE3TRADESVALUE":201842315.84,"ADMITTEDVALUE":201842315.84,"MATDATE":"2027-02-03","DURATION":2522,"YIELDATWAP":12.13,"IRICPICLOSE":null,"BEICLOSE":null,"COUPONPERCENT":null,"COUPONVALUE":null,"BUYBACKDATE":null,"LASTTRADEDATE":null,"FACEVALUE":1000,"CURRENCYID":"SUR","CBRCLOSE":null,"YIELDTOOFFER":null,"YIELDLASTCOUPON":null,"OFFERDATE":null,"FACEUNIT":"RUB"},{"BOARDID":"TQOB","TRADEDATE":"2015-02-06","SHORTNAME":"\u041E\u0424\u0417 26208","SECID":"SU26208RMFS7","NUMTRADES":0,"VALUE":0,"LOW":null,"HIGH":null,"CLOSE":null,"LEGALCLOSEPRICE":82.25,"ACCINT":32.06,"WAPRICE":null,"YIELDCLOSE":15.07,"OPEN":null,"VOLUME":0,"MARKETPRICE2":82.3035,"MARKETPRICE3":82.3035,"ADMITTEDQUOTE":82.3035,"MP2VALTRD":619128038,"MARKETPRICE3TRADESVALUE":619128038,"ADMITTEDVALUE":619128038,"MATDATE":"2019-02-27","DURATION":1234,"YIELDATWAP":null,"IRICPICLOSE":null,"BEICLOSE":null,"COUPONPERCENT":null,"COUPONVALUE":null,"BUYBACKDATE":null,"LASTTRADEDATE":null,"FACEVALUE":1000,"CURRENCYID":"SUR","CBRCLOSE":null,"YIELDTOOFFER":null,"YIELDLASTCOUPON":null,"OFFERDATE":null,"FACEUNIT":"RUB"},{"BOARDID":"TQOB","TRADEDATE":"2015-02-06","SHORTNAME":"\u041E\u0424\u0417 26209","SECID":"SU26209RMFS5","NUMTRADES":0,"VALUE":0,"LOW":null,"HIGH":null,"CLOSE":null,"LEGALCLOSEPRICE":76,"ACCINT":1.87,"WAPRICE":null,"YIELDCLOSE":15.55,"OPEN":null,"VOLUME":0,"MARKETPRICE2":74.4902,"MARKETPRICE3":74.5387,"ADMITTEDQUOTE":74.4902,"MP2VALTRD":252694739.5,"MARKETPRICE3TRADESVALUE":242293125.5,"ADMITTEDVALUE":252694739.5,"MATDATE":"2022-07-20","DURATION":2010,"YIELDATWAP":null,"IRICPICLOSE":null,"BEICLOSE":null,"COUPONPERCENT":null,"COUPONVALUE":null,"BUYBACKDATE":null,"LASTTRADEDATE":null,"FACEVALUE":1000,"CURRENCYID":"SUR","CBRCLOSE":null,"YIELDTOOFFER":null,"YIELDLASTCOUPON":null,"OFFERDATE":null,"FACEUNIT":"RUB"},{"BOARDID":"TQOB","TRADEDATE":"2015-02-06","SHORTNAME":"\u041E\u0424\u0417 26210","SECID":"SU26210RMFS3","NUMTRADES":0,"VALUE":0,"LOW":null,"HIGH":null,"CLOSE":null,"LEGALCLOSEPRICE":78,"ACCINT":9.5,"WAPRICE":null,"YIELDCLOSE":15.16,"OPEN":null,"VOLUME":0,"MARKETPRICE2":78.1297,"MARKETPRICE3":78.1508,"ADMITTEDQUOTE":78.1297,"MP2VALTRD":625430439.88,"MARKETPRICE3TRADESVALUE":617576409.7,"ADMITTEDVALUE":625430439.88,"MATDATE":"2019-12-11","DURATION":1479,"YIELDATWAP":null,"IRICPICLOSE":null,"BEICLOSE":null,"COUPONPERCENT":null,"COUPONVALUE":null,"BUYBACKDATE":null,"LASTTRADEDATE":null,"FACEVALUE":1000,"CURRENCYID":"SUR","CBRCLOSE":null,"YIELDTOOFFER":null,"YIELDLASTCOUPON":null,"OFFERDATE":null,"FACEUNIT":"RUB"},{"BOARDID":"TQOB","TRADEDATE":"2015-02-06","SHORTNAME":"\u041E\u0424\u0417 26211","SECID":"SU26211RMFS1","NUMTRADES":0,"VALUE":0,"LOW":null,"HIGH":null,"CLOSE":null,"LEGALCLOSEPRICE":73,"ACCINT":0.38,"WAPRICE":null,"YIELDCLOSE":13.28,"OPEN":null,"VOLUME":0,"MARKETPRICE2":71.1526,"MARKETPRICE3":72.9551,"ADMITTEDQUOTE":71.1526,"MP2VALTRD":177105339.02,"MARKETPRICE3TRADESVALUE":5540940.02,"ADMITTEDVALUE":177105339.02,"MATDATE":"2023-01-25","DURATION":2139,"YIELDATWAP":null,"IRICPICLOSE":null,"BEICLOSE":null,"COUPONPERCENT":null,"COUPONVALUE":null,"BUYBACKDATE":null,"LASTTRADEDATE":null,"FACEVALUE":1000,"CURRENCYID":"SUR","CBRCLOSE":null,"YIELDTOOFFER":null,"YIELDLASTCOUPON":null,"OFFERDATE":null,"FACEUNIT":"RUB"},{"BOARDID":"TQOB","TRADEDATE":"2015-02-06","SHORTNAME":"\u041E\u0424\u0417 26212","SECID":"SU26212RMFS9","NUMTRADES":2,"VALUE":7239.8,"LOW":65.5,"HIGH":68.98,"CLOSE":68.98,"LEGALCLOSEPRICE":69,"ACCINT":0.39,"WAPRICE":65.8164,"YIELDCLOSE":12.12,"OPEN":65.5,"VOLUME":11,"MARKETPRICE2":68.8469,"MARKETPRICE3":68.8469,"ADMITTEDQUOTE":68.8469,"MP2VALTRD":244644017.5,"MARKETPRICE3TRADESVALUE":244644017.5,"ADMITTEDVALUE":244644017.5,"MATDATE":"2028-01-19","DURATION":2776,"YIELDATWAP":12.81,"IRICPICLOSE":null,"BEICLOSE":null,"COUPONPERCENT":null,"COUPONVALUE":null,"BUYBACKDATE":null,"LASTTRADEDATE":null,"FACEVALUE":1000,"CURRENCYID":"SUR","CBRCLOSE":null,"YIELDTOOFFER":null,"YIELDLASTCOUPON":null,"OFFERDATE":null,"FACEUNIT":"RUB"},{"BOARDID":"TQOB","TRADEDATE":"2015-02-06","SHORTNAME":"\u041E\u0424\u0417 26214","SECID":"SU26214RMFS5","NUMTRADES":0,"VALUE":0,"LOW":null,"HIGH":null,"CLOSE":null,"LEGALCLOSEPRICE":76,"ACCINT":11.4,"WAPRICE":null,"YIELDCLOSE":14.78,"OPEN":null,"VOLUME":0,"MARKETPRICE2":71.8009,"MARKETPRICE3":71.8009,"ADMITTEDQUOTE":71.8009,"MP2VALTRD":78665814,"MARKETPRICE3TRADESVALUE":78665814,"ADMITTEDVALUE":78665814,"MATDATE":"2020-05-27","DURATION":1589,"YIELDATWAP":null,"IRICPICLOSE":null,"BEICLOSE":null,"COUPONPERCENT":null,"COUPONVALUE":null,"BUYBACKDATE":null,"LASTTRADEDATE":null,"FACEVALUE":1000,"CURRENCYID":"SUR","CBRCLOSE":null,"YIELDTOOFFER":null,"YIELDLASTCOUPON":null,"OFFERDATE":null,"FACEUNIT":"RUB"},{"BOARDID":"TQOB","TRADEDATE":"2015-02-06","SHORTNAME":"\u041E\u0424\u0417 26215","SECID":"SU26215RMFS2","NUMTRADES":0,"VALUE":0,"LOW":null,"HIGH":null,"CLOSE":null,"LEGALCLOSEPRICE":72.9557,"ACCINT":31.26,"WAPRICE":null,"YIELDCLOSE":9.06,"OPEN":null,"VOLUME":0,"MARKETPRICE2":null,"MARKETPRICE3":71.0471,"ADMITTEDQUOTE":null,"MP2VALTRD":0,"MARKETPRICE3TRADESVALUE":3666742.81,"ADMITTEDVALUE":0,"MATDATE":"2023-08-16","DURATION":2143,"YIELDATWAP":null,"IRICPICLOSE":null,"BEICLOSE":null,"COUPONPERCENT":null,"COUPONVALUE":null,"BUYBACKDATE":null,"LASTTRADEDATE":null,"FACEVALUE":1000,"CURRENCYID":"SUR","CBRCLOSE":null,"YIELDTOOFFER":null,"YIELDLASTCOUPON":null,"OFFERDATE":null,"FACEUNIT":"RUB"},{"BOARDID":"TQOB","TRADEDATE":"2015-02-06","SHORTNAME":"\u041E\u0424\u0417 26216","SECID":"SU26216RMFS0","NUMTRADES":0,"VALUE":0,"LOW":null,"HIGH":null,"CLOSE":null,"LEGALCLOSEPRICE":79,"ACCINT":14.5,"WAPRICE":null,"YIELDCLOSE":15.05,"OPEN":null,"VOLUME":0,"MARKETPRICE2":79.4329,"MARKETPRICE3":79.4329,"ADMITTEDQUOTE":79.4329,"MP2VALTRD":820703277.5,"MARKETPRICE3TRADESVALUE":820703277.5,"ADMITTEDVALUE":820703277.5,"MATDATE":"2019-05-15","DURATION":1331,"YIELDATWAP":null,"IRICPICLOSE":null,"BEICLOSE":null,"COUPONPERCENT":null,"COUPONVALUE":null,"BUYBACKDATE":null,"LASTTRADEDATE":null,"FACEVALUE":1000,"CURRENCYID":"SUR","CBRCLOSE":null,"YIELDTOOFFER":null,"YIELDLASTCOUPON":null,"OFFERDATE":null,"FACEUNIT":"RUB"},{"BOARDID":"TQOB","TRADEDATE":"2015-02-06","SHORTNAME":"\u041E\u0424\u0417 46005","SECID":"SU46005RMFS3","NUMTRADES":0,"VALUE":0,"LOW":null,"HIGH":null,"CLOSE":null,"LEGALCLOSEPRICE":80,"ACCINT":0,"WAPRICE":null,"YIELDCLOSE":10.24,"OPEN":null,"VOLUME":0,"MARKETPRICE2":null,"MARKETPRICE3":70.0558,"ADMITTEDQUOTE":null,"MP2VALTRD":0,"MARKETPRICE3TRADESVALUE":5022302.84,"ADMITTEDVALUE":0,"MATDATE":"2019-01-09","DURATION":1170,"YIELDATWAP":null,"IRICPICLOSE":null,"BEICLOSE":null,"COUPONPERCENT":null,"COUPONVALUE":null,"BUYBACKDATE":null,"LASTTRADEDATE":null,"FACEVALUE":1000,"CURRENCYID":"SUR","CBRCLOSE":null,"YIELDTOOFFER":null,"YIELDLASTCOUPON":null,"OFFERDATE":null,"FACEUNIT":"RUB"},{"BOARDID":"TQOB","TRADEDATE":"2015-02-06","SHORTNAME":"\u041E\u0424\u0417 46010","SECID":"SU46010RMFS3","NUMTRADES":0,"VALUE":0,"LOW":null,"HIGH":null,"CLOSE":null,"LEGALCLOSEPRICE":null,"ACCINT":67.67,"WAPRICE":null,"YIELDCLOSE":null,"OPEN":null,"VOLUME":0,"MARKETPRICE2":null,"MARKETPRICE3":null,"ADMITTEDQUOTE":null,"MP2VALTRD":0,"MARKETPRICE3TRADESVALUE":0,"ADMITTEDVALUE":0,"MATDATE":"2028-05-17","DURATION":null,"YIELDATWAP":null,"IRICPICLOSE":null,"BEICLOSE":null,"COUPONPERCENT":null,"COUPONVALUE":null,"BUYBACKDATE":null,"LASTTRADEDATE":null,"FACEVALUE":1000,"CURRENCYID":"SUR","CBRCLOSE":null,"YIELDTOOFFER":null,"YIELDLASTCOUPON":null,"OFFERDATE":null,"FACEUNIT":"RUB"},{"BOARDID":"TQOB","TRADEDATE":"2015-02-06","SHORTNAME":"\u041E\u0424\u0417 46011","SECID":"SU46011RMFS1","NUMTRADES":0,"VALUE":0,"LOW":null,"HIGH":null,"CLOSE":null,"LEGALCLOSEPRICE":91,"ACCINT":42.74,"WAPRICE":null,"YIELDCLOSE":5.88,"OPEN":null,"VOLUME":0,"MARKETPRICE2":91.1324,"MARKETPRICE3":91.17,"ADMITTEDQUOTE":91.1324,"MP2VALTRD":1576590.85,"MARKETPRICE3TRADESVALUE":1260880.68,"ADMITTEDVALUE":1576590.85,"MATDATE":"2025-08-20","DURATION":2090,"YIELDATWAP":null,"IRICPICLOSE":null,"BEICLOSE":null,"COUPONPERCENT":null,"COUPONVALUE":null,"BUYBACKDATE":null,"LASTTRADEDATE":null,"FACEVALUE":1000,"CURRENCYID":"SUR","CBRCLOSE":null,"YIELDTOOFFER":null,"YIELDLASTCOUPON":null,"OFFERDATE":null,"FACEUNIT":"RUB"},{"BOARDID":"TQOB","TRADEDATE":"2015-02-06","SHORTNAME":"\u041E\u0424\u0417 46012","SECID":"SU46012RMFS9","NUMTRADES":0,"VALUE":0,"LOW":null,"HIGH":null,"CLOSE":null,"LEGALCLOSEPRICE":51.8,"ACCINT":17.28,"WAPRICE":null,"YIELDCLOSE":11.25,"OPEN":null,"VOLUME":0,"MARKETPRICE2":null,"MARKETPRICE3":null,"ADMITTEDQUOTE":null,"MP2VALTRD":0,"MARKETPRICE3TRADESVALUE":0,"ADMITTEDVALUE":0,"MATDATE":"2029-09-05","DURATION":null,"YIELDATWAP":null,"IRICPICLOSE":null,"BEICLOSE":null,"COUPONPERCENT":null,"COUPONVALUE":null,"BUYBACKDATE":null,"LASTTRADEDATE":null,"FACEVALUE":1000,"CURRENCYID":"SUR","CBRCLOSE":null,"YIELDTOOFFER":null,"YIELDLASTCOUPON":null,"OFFERDATE":null,"FACEUNIT":"RUB"},{"BOARDID":"TQOB","TRADEDATE":"2015-02-06","SHORTNAME":"\u041E\u0424\u0417 46014","SECID":"SU46014RMFS5","NUMTRADES":0,"VALUE":0,"LOW":null,"HIGH":null,"CLOSE":null,"LEGALCLOSEPRICE":82.5,"ACCINT":14.96,"WAPRICE":null,"YIELDCLOSE":6.8,"OPEN":null,"VOLUME":0,"MARKETPRICE2":null,"MARKETPRICE3":83.6255,"ADMITTEDQUOTE":null,"MP2VALTRD":0,"MARKETPRICE3TRADESVALUE":2249109.15,"ADMITTEDVALUE":0,"MATDATE":"2018-08-29","DURATION":1049,"YIELDATWAP":null,"IRICPICLOSE":null,"BEICLOSE":null,"COUPONPERCENT":null,"COUPONVALUE":null,"BUYBACKDATE":null,"LASTTRADEDATE":null,"FACEVALUE":500,"CURRENCYID":"SUR","CBRCLOSE":null,"YIELDTOOFFER":null,"YIELDLASTCOUPON":null,"OFFERDATE":null,"FACEUNIT":"RUB"},{"BOARDID":"TQOB","TRADEDATE":"2015-02-06","SHORTNAME":"\u041E\u0424\u0417 46017","SECID":"SU46017RMFS8","NUMTRADES":0,"VALUE":0,"LOW":null,"HIGH":null,"CLOSE":null,"LEGALCLOSEPRICE":93.5,"ACCINT":0.33,"WAPRICE":null,"YIELDCLOSE":9.83,"OPEN":null,"VOLUME":0,"MARKETPRICE2":93.0118,"MARKETPRICE3":93.0118,"ADMITTEDQUOTE":93.0118,"MP2VALTRD":3934400.85,"MARKETPRICE3TRADESVALUE":3934400.85,"ADMITTEDVALUE":3934400.85,"MATDATE":"2016-08-03","DURATION":345,"YIELDATWAP":null,"IRICPICLOSE":null,"BEICLOSE":null,"COUPONPERCENT":null,"COUPONVALUE":null,"BUYBACKDATE":null,"LASTTRADEDATE":null,"FACEVALUE":1000,"CURRENCYID":"SUR","CBRCLOSE":null,"YIELDTOOFFER":null,"YIELDLASTCOUPON":null,"OFFERDATE":null,"FACEUNIT":"RUR"},{"BOARDID":"TQOB","TRADEDATE":"2015-02-06","SHORTNAME":"\u041E\u0424\u0417 46018","SECID":"SU46018RMFS6","NUMTRADES":0,"VALUE":0,"LOW":null,"HIGH":null,"CLOSE":null,"LEGALCLOSEPRICE":73.35,"ACCINT":11.58,"WAPRICE":null,"YIELDCLOSE":13.37,"OPEN":null,"VOLUME":0,"MARKETPRICE2":72.4962,"MARKETPRICE3":72.4976,"ADMITTEDQUOTE":72.4962,"MP2VALTRD":11268081.5,"MARKETPRICE3TRADESVALUE":11257431.5,"ADMITTEDVALUE":11268081.5,"MATDATE":"2021-11-24","DURATION":1689,"YIELDATWAP":null,"IRICPICLOSE":null,"BEICLOSE":null,"COUPONPERCENT":null,"COUPONVALUE":null,"BUYBACKDATE":null,"LASTTRADEDATE":null,"FACEVALUE":1000,"CURRENCYID":"SUR","CBRCLOSE":null,"YIELDTOOFFER":null,"YIELDLASTCOUPON":null,"OFFERDATE":null,"FACEUNIT":"RUB"},{"BOARDID":"TQOB","TRADEDATE":"2015-02-06","SHORTNAME":"\u041E\u0424\u0417 46019","SECID":"SU46019RMFS4","NUMTRADES":0,"VALUE":0,"LOW":null,"HIGH":null,"CLOSE":null,"LEGALCLOSEPRICE":70.0701,"ACCINT":13.93,"WAPRICE":null,"YIELDCLOSE":10.71,"OPEN":null,"VOLUME":0,"MARKETPRICE2":null,"MARKETPRICE3":70.6963,"ADMITTEDQUOTE":null,"MP2VALTRD":0,"MARKETPRICE3TRADESVALUE":503357.43,"ADMITTEDVALUE":0,"MATDATE":"2019-03-20","DURATION":777,"YIELDATWAP":null,"IRICPICLOSE":null,"BEICLOSE":null,"COUPONPERCENT":null,"COUPONVALUE":null,"BUYBACKDATE":null,"LASTTRADEDATE":null,"FACEVALUE":800,"CURRENCYID":"SUR","CBRCLOSE":null,"YIELDTOOFFER":null,"YIELDLASTCOUPON":null,"OFFERDATE":null,"FACEUNIT":"RUB"},{"BOARDID":"TQOB","TRADEDATE":"2015-02-06","SHORTNAME":"\u041E\u0424\u0417 46020","SECID":"SU46020RMFS2","NUMTRADES":0,"VALUE":0,"LOW":null,"HIGH":null,"CLOSE":null,"LEGALCLOSEPRICE":60,"ACCINT":33.46,"WAPRICE":null,"YIELDCLOSE":13.88,"OPEN":null,"VOLUME":0,"MARKETPRICE2":60,"MARKETPRICE3":60,"ADMITTEDQUOTE":60,"MP2VALTRD":8891400,"MARKETPRICE3TRADESVALUE":8891400,"ADMITTEDVALUE":8891400,"MATDATE":"2036-02-06","DURATION":2994,"YIELDATWAP":null,"IRICPICLOSE":null,"BEICLOSE":null,"COUPONPERCENT":null,"COUPONVALUE":null,"BUYBACKDATE":null,"LASTTRADEDATE":null,"FACEVALUE":1000,"CURRENCYID":"SUR","CBRCLOSE":null,"YIELDTOOFFER":null,"YIELDLASTCOUPON":null,"OFFERDATE":null,"FACEUNIT":"RUB"},{"BOARDID":"TQOB","TRADEDATE":"2015-02-06","SHORTNAME":"\u041E\u0424\u0417 46021","SECID":"SU46021RMFS0","NUMTRADES":0,"VALUE":0,"LOW":null,"HIGH":null,"CLOSE":null,"LEGALCLOSEPRICE":81.5,"ACCINT":26.67,"WAPRICE":null,"YIELDCLOSE":12.42,"OPEN":null,"VOLUME":0,"MARKETPRICE2":81.1128,"MARKETPRICE3":81.1072,"ADMITTEDQUOTE":81.1128,"MP2VALTRD":46641469.3,"MARKETPRICE3TRADESVALUE":46333279.65,"ADMITTEDVALUE":46641469.3,"MATDATE":"2018-08-08","DURATION":981,"YIELDATWAP":null,"IRICPICLOSE":null,"BEICLOSE":null,"COUPONPERCENT":null,"COUPONVALUE":null,"BUYBACKDATE":null,"LASTTRADEDATE":null,"FACEVALUE":1000,"CURRENCYID":"SUR","CBRCLOSE":null,"YIELDTOOFFER":null,"YIELDLASTCOUPON":null,"OFFERDATE":null,"FACEUNIT":"RUB"},{"BOARDID":"TQOB","TRADEDATE":"2015-02-06","SHORTNAME":"\u041E\u0424\u0417 46022","SECID":"SU46022RMFS8","NUMTRADES":0,"VALUE":0,"LOW":null,"HIGH":null,"CLOSE":null,"LEGALCLOSEPRICE":65,"ACCINT":2.63,"WAPRICE":null,"YIELDCLOSE":13.69,"OPEN":null,"VOLUME":0,"MARKETPRICE2":65.1275,"MARKETPRICE3":65.1275,"ADMITTEDQUOTE":65.1275,"MP2VALTRD":562050.12,"MARKETPRICE3TRADESVALUE":562050.12,"ADMITTEDVALUE":562050.12,"MATDATE":"2023-07-19","DURATION":2185,"YIELDATWAP":null,"IRICPICLOSE":null,"BEICLOSE":null,"COUPONPERCENT":null,"COUPONVALUE":null,"BUYBACKDATE":null,"LASTTRADEDATE":null,"FACEVALUE":1000,"CURRENCYID":"SUR","CBRCLOSE":null,"YIELDTOOFFER":null,"YIELDLASTCOUPON":null,"OFFERDATE":null,"FACEUNIT":"RUB"},{"BOARDID":"TQOB","TRADEDATE":"2015-02-06","SHORTNAME":"\u041E\u0424\u0417 46023","SECID":"SU46023RMFS6","NUMTRADES":0,"VALUE":0,"LOW":null,"HIGH":null,"CLOSE":null,"LEGALCLOSEPRICE":100,"ACCINT":0.22,"WAPRICE":null,"YIELDCLOSE":7.22,"OPEN":null,"VOLUME":0,"MARKETPRICE2":105.1739,"MARKETPRICE3":106.6721,"ADMITTEDQUOTE":105.1739,"MP2VALTRD":662595.46,"MARKETPRICE3TRADESVALUE":526960.4,"ADMITTEDVALUE":662595.46,"MATDATE":"2026-07-23","DURATION":1858,"YIELDATWAP":null,"IRICPICLOSE":null,"BEICLOSE":null,"COUPONPERCENT":null,"COUPONVALUE":null,"BUYBACKDATE":null,"LASTTRADEDATE":null,"FACEVALUE":1000,"CURRENCYID":"SUR","CBRCLOSE":null,"YIELDTOOFFER":null,"YIELDLASTCOUPON":null,"OFFERDATE":null,"FACEUNIT":"RUB"},{"BOARDID":"TQOB","TRADEDATE":"2015-02-06","SHORTNAME":"\u041E\u0424\u0417 48001","SECID":"SU48001RMFS0","NUMTRADES":0,"VALUE":0,"LOW":null,"HIGH":null,"CLOSE":null,"LEGALCLOSEPRICE":89,"ACCINT":10.19,"WAPRICE":null,"YIELDCLOSE":5.14,"OPEN":null,"VOLUME":0,"MARKETPRICE2":null,"MARKETPRICE3":77.9069,"ADMITTEDQUOTE":null,"MP2VALTRD":0,"MARKETPRICE3TRADESVALUE":608920.37,"ADMITTEDVALUE":0,"MATDATE":"2018-10-31","DURATION":721,"YIELDATWAP":null,"IRICPICLOSE":null,"BEICLOSE":null,"COUPONPERCENT":null,"COUPONVALUE":null,"BUYBACKDATE":null,"LASTTRADEDATE":null,"FACEVALUE":800,"CURRENCYID":"SUR","CBRCLOSE":null,"YIELDTOOFFER":null,"YIELDLASTCOUPON":null,"OFFERDATE":null,"FACEUNIT":"RUB"}]